mcp_seniverse_weather_demo/__init__.py
mcp_seniverse_weather_demo/__main__.py
mcp_seniverse_weather_demo/server.py
mcp_seniverse_weather_demo-0.0.99.dist-info/METADATA
mcp_seniverse_weather_demo-0.0.99.dist-info/WHEEL
mcp_seniverse_weather_demo-0.0.99.dist-info/entry_points.txt
mcp_seniverse_weather_demo-0.0.99.dist-info/RECORD
