Metadata-Version: 2.4
Name: mcp-seniverse-weather-demo
Version: 0.0.99
Summary: 使用Seniverse API到天气预报MCP Server
Requires-Python: >=3.11
Requires-Dist: hatchling>=1.27.0
Requires-Dist: mcp[cli]>=1.6.0
Requires-Dist: requests>=2.32.4
